nonebot_plugin_whats_talk_gemini/__init__.py
nonebot_plugin_whats_talk_gemini/config.py
nonebot_plugin_whats_talk_gemini-0.0.5.dist-info/LICENSE
nonebot_plugin_whats_talk_gemini-0.0.5.dist-info/METADATA
nonebot_plugin_whats_talk_gemini-0.0.5.dist-info/WHEEL
nonebot_plugin_whats_talk_gemini-0.0.5.dist-info/RECORD
